upid-0.2.0.dist-info/METADATA
upid-0.2.0.dist-info/WHEEL
upid-0.2.0.dist-info/licenses/LICENSE
upid/__init__.py
upid/__main__.py
upid/b32.py
upid/consts.py
upid/core.py
upid/py.typed
upid-0.2.0.dist-info/RECORD
