Metadata-Version: 2.1
Name: upid
Version: 0.2.0
Summary: Universally Unique Prefixed Lexicographically Sortable Identifier
Keywords: UUID,id,database
Home-page: https://github.com/carderne/upid
Author-Email: Chris Arderne <chris@rdrn.me>
License: MIT License
Classifier: Environment :: Console
Classifier: Intended Audience :: Developers
Classifier: License :: OSI Approved :: MIT License
Classifier: Operating System :: Unix
Classifier: Programming Language :: Python
Classifier: Programming Language :: Python :: 3.9
Classifier: Programming Language :: Python :: 3.10
Classifier: Programming Language :: Python :: 3.11
Classifier: Programming Language :: Python :: 3.12
Classifier: Topic :: Software Development :: Libraries
Project-URL: Homepage, https://github.com/carderne/upid
Project-URL: Repository, https://github.com/carderne/upid
Requires-Python: >=3.9
